mcpturbo_web_stack/__init__.py
mcpturbo_web_stack/main.py
mcpturbo_web_stack-1.0.0.dist-info/licenses/LICENSE
mcpturbo_web_stack-1.0.0.dist-info/METADATA
mcpturbo_web_stack-1.0.0.dist-info/WHEEL
mcpturbo_web_stack-1.0.0.dist-info/top_level.txt
mcpturbo_web_stack-1.0.0.dist-info/RECORD
