Metadata-Version: 2.4
Name: mcpturbo-web-stack
Version: 1.0.0
Summary: MCPTurbo - Web Development Stack
Author-email: Federico Monfasani <fmonfasani@gmail.com>
License: MIT
Project-URL: Homepage, https://github.com/fmonfasani/{project_name}
Project-URL: Repository, https://github.com/fmonfasani/{project_name}
Project-URL: Issues, https://github.com/fmonfasani/{project_name}/issues
Project-URL: Documentation, https://mcpturbo.dev/docs/{project_name.replace('mcpturbo-', '')}
Keywords: mcpturbo,agents,mcp,automation,ai
Classifier: Development Status :: 4 - Beta
Classifier: Intended Audience :: Developers
Classifier: License :: OSI Approved :: MIT License
Classifier: Programming Language :: Python :: 3
Classifier: Programming Language :: Python :: 3.9
Classifier: Programming Language :: Python :: 3.10
Classifier: Programming Language :: Python :: 3.11
Classifier: Programming Language :: Python :: 3.12
Classifier: Topic :: Software Development :: Libraries :: Python Modules
Classifier: Topic :: Scientific/Engineering :: Artificial Intelligence
Requires-Python: >=3.9
License-File: LICENSE
Requires-Dist: pydantic>=2.0.0
Requires-Dist: typing-extensions>=4.0.0
Requires-Dist: mcpturbo-core>=1.0.0
Requires-Dist: mcpturbo-agents>=1.0.0
Requires-Dist: mcpturbo-generators>=1.0.0
Requires-Dist: mcpturbo-templates>=1.0.0
Requires-Dist: mcpturbo-cli>=1.0.0
Provides-Extra: dev
Requires-Dist: pytest>=7.0.0; extra == "dev"
Requires-Dist: pytest-asyncio>=0.21.0; extra == "dev"
Requires-Dist: black>=23.0.0; extra == "dev"
Requires-Dist: isort>=5.12.0; extra == "dev"
Requires-Dist: mypy>=1.0.0; extra == "dev"
Requires-Dist: flake8>=6.0.0; extra == "dev"
Provides-Extra: test
Requires-Dist: pytest>=7.0.0; extra == "test"
Requires-Dist: pytest-asyncio>=0.21.0; extra == "test"
Requires-Dist: pytest-cov>=4.0.0; extra == "test"
Dynamic: license-file
